seven_shop/__init__.py
seven_shop/route.py
seven_shop/handlers/__init__.py
seven_shop/handlers/cart.py
seven_shop/handlers/category.py
seven_shop/handlers/coupon.py
seven_shop/handlers/goods.py
seven_shop/handlers/init.py
seven_shop/handlers/order.py
seven_shop/handlers/seven_base.py
seven_shop/libs/__init__.py
seven_shop/libs/customize/__init__.py
seven_shop/libs/customize/coupon_helper.py
seven_shop/libs/customize/order_helper.py
seven_shop/libs/customize/user_helper.py
seven_shop/libs/customize/wechat_helper.py
seven_shop/models/__init__.py
seven_shop/models/db_models/__init__.py
seven_shop/models/db_models/cart/__init__.py
seven_shop/models/db_models/cart/cart_model.py
seven_shop/models/db_models/cart/cart_model_ex.py
seven_shop/models/db_models/coupon/__init__.py
seven_shop/models/db_models/coupon/coupon_goods_model.py
seven_shop/models/db_models/coupon/coupon_grant_model.py
seven_shop/models/db_models/coupon/coupon_model.py
seven_shop/models/db_models/coupon/coupon_model_ex.py
seven_shop/models/db_models/coupon/coupon_record_model.py
seven_shop/models/db_models/goods/__init__.py
seven_shop/models/db_models/goods/goods_model.py
seven_shop/models/db_models/goods/goods_model_ex.py
seven_shop/models/db_models/goods/goods_recommend_model.py
seven_shop/models/db_models/goods/goods_sku_model.py
seven_shop/models/db_models/goods/goods_sku_model_ex.py
seven_shop/models/db_models/inventory/__init__.py
seven_shop/models/db_models/inventory/inventory_change_model.py
seven_shop/models/db_models/inventory/inventory_model.py
seven_shop/models/db_models/inventory/inventory_model_ex.py
seven_shop/models/db_models/order/__init__.py
seven_shop/models/db_models/order/order_goods_model.py
seven_shop/models/db_models/order/order_goods_model_ex.py
seven_shop/models/db_models/order/order_model.py
seven_shop/models/db_models/order/order_model_ex.py
seven_shop/models/db_models/order/order_refund_goods_model.py
seven_shop/models/db_models/order/order_refund_goods_model_ex.py
seven_shop-1.0.53.dist-info/LICENSE
seven_shop-1.0.53.dist-info/METADATA
seven_shop-1.0.53.dist-info/WHEEL
seven_shop-1.0.53.dist-info/top_level.txt
seven_shop-1.0.53.dist-info/RECORD
